{"trial_id": "abe94f65ad91ced664f93e311a61eea9", "hyperparameters": {"space": [{"class_name": "Int", "config": {"name": "units", "default": null, "conditions": [], "min_value": 8, "max_value": 512, "step": 32, "sampling": null}}, {"class_name": "Choice", "config": {"name": "0.001", "default": 0.01, "conditions": [], "values": [0.01, 0.001, 0.0001], "ordered": true}}], "values": {"units": 40, "0.001": 0.01, "tuner/epochs": 2, "tuner/initial_epoch": 0, "tuner/bracket": 3, "tuner/round": 0}}, "metrics": {"metrics": {"loss": {"direction": "min", "observations": [{"value": [1.100309133529663], "step": 0}]}, "accuracy": {"direction": "max", "observations": [{"value": [0.2488815188407898], "step": 0}]}, "val_loss": {"direction": "min", "observations": [{"value": [1.010797381401062], "step": 0}]}, "val_accuracy": {"direction": "max", "observations": [{"value": [0.24473683536052704], "step": 0}]}}}, "score": 0.24473683536052704, "best_step": 0, "status": "COMPLETED"}